f1_fantasy/__init__.py
f1_fantasy/__main__.py
f1_fantasy/consts.py
f1_fantasy/data/input/chips.csv
f1_fantasy/data/input/current_team.csv
f1_fantasy/data/input/finishing_positions_qualifying.csv
f1_fantasy/data/input/finishing_positions_race.csv
f1_fantasy/data/input/ignore_constructors.csv
f1_fantasy/data/input/ignore_drivers.csv
f1_fantasy/data/input/price_constructors.csv
f1_fantasy/data/input/price_drivers.csv
f1_fantasy/data/input/special_points.csv
f1_fantasy/game_objects.py
f1_fantasy/main.py
f1_fantasy/models.py
f1_fantasy/settings.py
f1_fantasy-0.6.1.dist-info/LICENSE
f1_fantasy-0.6.1.dist-info/METADATA
f1_fantasy-0.6.1.dist-info/WHEEL
f1_fantasy-0.6.1.dist-info/entry_points.txt
f1_fantasy-0.6.1.dist-info/RECORD
